.gitignore
LICENSE.md
Pipfile
Pipfile.lock
README.md
app.py
pytest.ini
requirements.txt
setup.cfg
setup.py
dash_okta_auth/__init__.py
dash_okta_auth/auth.py
dash_okta_auth/okta_oauth.py
dash_okta_auth.egg-info/PKG-INFO
dash_okta_auth.egg-info/SOURCES.txt
dash_okta_auth.egg-info/dependency_links.txt
dash_okta_auth.egg-info/not-zip-safe
dash_okta_auth.egg-info/requires.txt
dash_okta_auth.egg-info/top_level.txt
tests/__init__.py
tests/test_import.py