Metadata-Version: 2.1
Name: dash-okta-auth
Version: 0.0.1
Summary: Dash Okta Auth
Home-page: https://github.com/fspijkerman/dash-okta-auth
Author: Frank Spijkerman
Author-email: fspijkerman@schubergphilis.com
License: MIT
Platform: UNKNOWN
Classifier: License :: OSI Approved :: MIT License
Classifier: Programming Language :: Python
Classifier: Programming Language :: Python :: Implementation :: CPython
